django_rest_fuzzysearch-0.5.0.dist-info/DESCRIPTION.rst
django_rest_fuzzysearch-0.5.0.dist-info/METADATA
django_rest_fuzzysearch-0.5.0.dist-info/RECORD
django_rest_fuzzysearch-0.5.0.dist-info/WHEEL
django_rest_fuzzysearch-0.5.0.dist-info/metadata.json
django_rest_fuzzysearch-0.5.0.dist-info/top_level.txt
rest_fuzzysearch/__init__.py
rest_fuzzysearch/mixin.py
rest_fuzzysearch/search.py
rest_fuzzysearch/sort.py
